<?xml version="1.0" ?><annotation>
    <filename>AllianceVsArtisans_BO2_2_1_4.png</filename>
    <version>v3.0</version>
    <review_status>passed</review_status>
    <time_elapsed>120</time_elapsed>
    <img_label/>
    <size>
        <width>174</width>
        <height>173</height>
    </size>
    <padding_pxt>
        <padding_x>76</padding_x>
        <padding_y>43</padding_y>
    </padding_pxt>
    <object>
        <name>armor</name>
        <armor_class>4</armor_class>
        <armor_color>red</armor_color>
        <generated>0</generated>
        <is_incorrect>0</is_incorrect>
        <bndbox>
            <xmin>96</xmin>
            <ymin>69</ymin>
            <xmax>110</xmax>
            <ymax>88</ymax>
        </bndbox>
    </object>
    <object>
        <name>armor</name>
        <armor_class>4</armor_class>
        <armor_color>red</armor_color>
        <generated>0</generated>
        <is_incorrect>0</is_incorrect>
        <bndbox>
            <xmin>70</xmin>
            <ymin>101</ymin>
            <xmax>93</xmax>
            <ymax>116</ymax>
        </bndbox>
    </object>
    
    
    
    
    
    
    
    
    
    
    
    
    
    
    
    <object>
        <name>car</name>
        <difficulty>0</difficulty>
        <generated>0</generated>
        <is_incorrect>0</is_incorrect>
        <bndbox>
            <xmin>50</xmin>
            <ymin>50</ymin>
            <xmax>124</xmax>
            <ymax>123</ymax>
        </bndbox>
    </object>
    
    
    
</annotation>